{"timestamp":"2026-04-21T00:00:00.000Z","exceptionType":"TypeError","targetFile":"src/auth/middleware.ts","targetLine":42,"suggestedFix":"Check for null/undefined values before accessing properties. Add a null guard or optional chaining (?.).","confidence":0.8}
{"timestamp":"2026-04-21T00:01:00.000Z","exceptionType":"ReferenceError","targetFile":"src/api/routes.ts","targetLine":18,"suggestedFix":"Ensure the variable is declared before use. Check import/require statements.","confidence":0.8}
{"timestamp":"2026-04-21T00:02:00.000Z","exceptionType":"ENOENT","targetFile":"src/config/loader.ts","targetLine":55,"suggestedFix":"The file does not exist. Check the path and ensure the file was created before reading.","confidence":0.8}
{"timestamp":"2026-04-21T00:03:00.000Z","exceptionType":"Cannot read properties of undefined","targetFile":"src/db/query.ts","targetLine":77,"suggestedFix":"Add a null guard: check if the object exists before accessing its properties.","confidence":0.8}
{"timestamp":"2026-04-21T00:04:00.000Z","exceptionType":"is not a function","targetFile":"src/utils/helpers.ts","targetLine":23,"suggestedFix":"Verify the function exists and is exported. Check the import statement.","confidence":0.8}
